pilot/__init__.py
pilot/base/__init__.py
pilot/base/ai_call.py
pilot/base/ai_info.py
pilot/base/chage_file_tag_base.py
pilot/base/db_operation_base.py
pilot/base/delete_commnents_base.py
pilot/base/file_operation.py
pilot/base/get_file_encoding.py
pilot/base/make_parsing_java_file_order_base.py
pilot/base/split_file_base.py
pilot/client/__init__.py
pilot/client/ai_client.py
pilot/config/__init__.py
pilot/config/config_reader.py
pilot/control/__init__.py
pilot/control/control_interface.py
pilot/control/impl/__init__.py
pilot/control/impl/base_controller.py
pilot/conver/__init__.py
pilot/conver/commentRemover.py
pilot/conver/converfileEncodding.py
pilot/create_python/__init__.py
pilot/create_python/create_python.py
pilot/create_python/config/__init__.py
pilot/create_python/config/create_file.py
pilot/create_python/sample/__init__.py
pilot/create_python/sample/child_sample/__init__.py
pilot/create_python/sample/child_sample/job/__init__.py
pilot/create_python/sample/config/__init__.py
pilot/create_python/sample/config/properties.py
pilot/db/__init__.py
pilot/db/create_table.py
pilot/db/db_connect.py
pilot/db/db_main.py
pilot/db/db_util.py
pilot/db/sql_executor.py
pilot/db/sql_loader.py
pilot/db/sql_service.py
pilot/db/ddl/__init__.py
pilot/db/dml/__init__.py
pilot/file_tool/__init__.py
pilot/file_tool/create_prompt_file.py
pilot/file_tool/json_file_tool.py
pilot/generater/__init__.py
pilot/generater/vertexai.py
pilot/job/__init__.py
pilot/job/job_interface.py
pilot/job/base/__init__.py
pilot/job/base/convert/__init__.py
pilot/job/base/convert/delimiterSwitcherJob.py
pilot/job/base/convert/encodingTransformerJob.py
pilot/job/base/convert/tabReplaceJob.py
pilot/job/base/generate/__init__.py
pilot/job/base/generate/generateJsonBaseJob.py
pilot/job/base/generate/generateTextBaseJob.py
pilot/job/base/program/__init__.py
pilot/job/base/program/cobol/__init__.py
pilot/job/base/program/cobol/convert/__init__.py
pilot/job/base/program/cobol/convert/spitPreDigit.py
pilot_linkstec-0.0.104.dist-info/licenses/LICENSE
pilot_linkstec-0.0.104.dist-info/METADATA
pilot_linkstec-0.0.104.dist-info/WHEEL
pilot_linkstec-0.0.104.dist-info/top_level.txt
pilot_linkstec-0.0.104.dist-info/RECORD
